csvtojsonlib.py
csvtojsonlib-1.1.3.dist-info/LICENSE
csvtojsonlib-1.1.3.dist-info/METADATA
csvtojsonlib-1.1.3.dist-info/WHEEL
csvtojsonlib-1.1.3.dist-info/top_level.txt
csvtojsonlib-1.1.3.dist-info/RECORD
